{
  "last_update": "2026-03-26T19:22:45.010917+00:00",
  "portfolio_value": 1000.0,
  "run_count": 147,
  "positions": {
    "BTC": {
      "symbol": "BTC",
      "state": "FLAT",
      "position_size": 0.0,
      "entry_time": null,
      "entry_price": 0.0,
      "entry_prediction": 0.0,
      "hours_held": 0,
      "api_fail_count": 0,
      "frozen": false,
      "last_update": "2026-03-26T19:22:18.464725+00:00",
      "history": []
    },
    "ETH": {
      "symbol": "ETH",
      "state": "FLAT",
      "position_size": 0.0,
      "entry_time": null,
      "entry_price": 0.0,
      "entry_prediction": 0.0,
      "hours_held": 0,
      "api_fail_count": 0,
      "frozen": false,
      "last_update": "2026-03-26T19:22:25.043133+00:00",
      "history": []
    },
    "SOL": {
      "symbol": "SOL",
      "state": "FLAT",
      "position_size": 0.0,
      "entry_time": null,
      "entry_price": 0.0,
      "entry_prediction": 0.0,
      "hours_held": 0,
      "api_fail_count": 0,
      "frozen": false,
      "last_update": "2026-03-26T19:22:32.225783+00:00",
      "history": []
    },
    "AVAX": {
      "symbol": "AVAX",
      "state": "FLAT",
      "position_size": 0.0,
      "entry_time": null,
      "entry_price": 0.0,
      "entry_prediction": 0.0,
      "hours_held": 0,
      "api_fail_count": 0,
      "frozen": false,
      "last_update": "2026-03-26T19:22:38.658307+00:00",
      "history": []
    },
    "XRP": {
      "symbol": "XRP",
      "state": "FLAT",
      "position_size": 0.0,
      "entry_time": null,
      "entry_price": 0.0,
      "entry_prediction": 0.0,
      "hours_held": 0,
      "api_fail_count": 0,
      "frozen": false,
      "last_update": "2026-03-26T19:22:45.010877+00:00",
      "history": []
    }
  }
}