{
  "last_update": "2026-05-31T20:20:12.527724+00:00",
  "portfolio_value": 1000.0,
  "run_count": 925,
  "positions": {
    "BTC": {
      "symbol": "BTC",
      "state": "FLAT",
      "position_size": 0.0,
      "entry_time": null,
      "entry_price": 0.0,
      "entry_prediction": 0.0,
      "hours_held": 0,
      "api_fail_count": 0,
      "frozen": false,
      "last_update": "2026-05-31T20:19:47.498179+00:00",
      "history": []
    },
    "ETH": {
      "symbol": "ETH",
      "state": "FLAT",
      "position_size": 0.0,
      "entry_time": null,
      "entry_price": 0.0,
      "entry_prediction": 0.0,
      "hours_held": 0,
      "api_fail_count": 0,
      "frozen": false,
      "last_update": "2026-05-31T20:19:54.031570+00:00",
      "history": []
    },
    "SOL": {
      "symbol": "SOL",
      "state": "FLAT",
      "position_size": 0.0,
      "entry_time": null,
      "entry_price": 0.0,
      "entry_prediction": 0.0,
      "hours_held": 0,
      "api_fail_count": 0,
      "frozen": false,
      "last_update": "2026-05-31T20:20:00.168757+00:00",
      "history": []
    },
    "AVAX": {
      "symbol": "AVAX",
      "state": "FLAT",
      "position_size": 0.0,
      "entry_time": null,
      "entry_price": 0.0,
      "entry_prediction": 0.0,
      "hours_held": 0,
      "api_fail_count": 0,
      "frozen": false,
      "last_update": "2026-05-31T20:20:06.289731+00:00",
      "history": []
    },
    "XRP": {
      "symbol": "XRP",
      "state": "FLAT",
      "position_size": 0.0,
      "entry_time": null,
      "entry_price": 0.0,
      "entry_prediction": 0.0,
      "hours_held": 0,
      "api_fail_count": 0,
      "frozen": false,
      "last_update": "2026-05-31T20:20:12.527687+00:00",
      "history": []
    }
  }
}